gitfunctions/__init__.py
gitfunctions/gitfunctions.py
gitfunctions-0.0.3.dist-info/METADATA
gitfunctions-0.0.3.dist-info/WHEEL
gitfunctions-0.0.3.dist-info/top_level.txt
gitfunctions-0.0.3.dist-info/RECORD
