Metadata-Version: 2.1
Name: gitfunctions
Version: 0.0.3
Summary: Lib for git functions
Home-page: https://github.com/strapbooll/git-functions
Author: strapbooll
Author-email: rximenez97@gmail.com
License: UNKNOWN
Platform: UNKNOWN
Requires-Dist: GitPython
